JiqiXuexiXunlianMijiMachineLearningYearningZhongwenban/README.md
JiqiXuexiXunlianMijiMachineLearningYearningZhongwenban/__init__.py
JiqiXuexiXunlianMijiMachineLearningYearningZhongwenban/__main__.py
JiqiXuexiXunlianMijiMachineLearningYearningZhongwenban/file.pdf
JiqiXuexiXunlianMijiMachineLearningYearningZhongwenban/index.html
jiqi_xuexi_xunlian_miji_machine_learning_yearning_zhongwenban-2024.3.3.0.dist-info/METADATA
jiqi_xuexi_xunlian_miji_machine_learning_yearning_zhongwenban-2024.3.3.0.dist-info/WHEEL
jiqi_xuexi_xunlian_miji_machine_learning_yearning_zhongwenban-2024.3.3.0.dist-info/entry_points.txt
jiqi_xuexi_xunlian_miji_machine_learning_yearning_zhongwenban-2024.3.3.0.dist-info/top_level.txt
jiqi_xuexi_xunlian_miji_machine_learning_yearning_zhongwenban-2024.3.3.0.dist-info/RECORD
